arial_distance/__init__.py
arial_distance/arial_distance.py
arial_distance-0.2.0.dist-info/METADATA
arial_distance-0.2.0.dist-info/WHEEL
arial_distance-0.2.0.dist-info/top_level.txt
arial_distance-0.2.0.dist-info/RECORD
