Metadata-Version: 2.1
Name: arial-distance
Version: 0.2.0
Summary: A library for calculating arial distance between two coordinates
Home-page: https://github.com/Sharad2124Ingle/arial_distance
Author: Sharad Ingle
Author-email: shrdingle@gmail.com
Classifier: Programming Language :: Python :: 3
Classifier: License :: OSI Approved :: MIT License
Classifier: Operating System :: OS Independent
Requires-Python: >=3.6
